edri/__init__.py
edri/abstract/__init__.py
edri/abstract/manager/__init__.py
edri/abstract/manager/manager_base.py
edri/abstract/manager/manager_priority_base.py
edri/abstract/manager/worker.py
edri/abstract/worker/__init__.py
edri/abstract/worker/worker.py
edri/abstract/worker/worker_process.py
edri/abstract/worker/worker_thread.py
edri/api/__init__.py
edri/api/broker.py
edri/api/listener.py
edri/api/middleware.py
edri/api/dataclass/__init__.py
edri/api/dataclass/api_event.py
edri/api/dataclass/client.py
edri/api/dataclass/file.py
edri/api/dataclass/range.py
edri/api/extensions/__init__.py
edri/api/extensions/url_extension.py
edri/api/extensions/url_prefix.py
edri/api/handlers/__init__.py
edri/api/handlers/base_handler.py
edri/api/handlers/html_handler.py
edri/api/handlers/http_handler.py
edri/api/handlers/rest_handler.py
edri/api/handlers/websocket_handler.py
edri/api/static_pages/documentation.j2
edri/api/static_pages/health_check_status.j2
edri/api/static_pages/status_300.j2
edri/api/static_pages/status_400.j2
edri/api/static_pages/status_500.j2
edri/config/__init__.py
edri/config/constant.py
edri/config/setting.py
edri/dataclass/__init__.py
edri/dataclass/event.py
edri/dataclass/health_checker.py
edri/dataclass/injection.py
edri/dataclass/response.py
edri/dataclass/directive/__init__.py
edri/dataclass/directive/base.py
edri/dataclass/directive/html.py
edri/dataclass/directive/http.py
edri/events/__init__.py
edri/events/api/__init__.py
edri/events/api/client/__init__.py
edri/events/api/client/documentation.py
edri/events/api/client/register.py
edri/events/api/client/unregister.py
edri/events/api/group/__init__.py
edri/events/api/group/client.py
edri/events/api/group/manage.py
edri/events/api/manage/__init__.py
edri/events/api/manage/list_registered.py
edri/events/api/manage/register.py
edri/events/api/manage/unregister.py
edri/events/api/manage/unregister_all.py
edri/events/edri/__init__.py
edri/events/edri/group/__init__.py
edri/events/edri/group/manager.py
edri-2025.12.3.dist-info/METADATA
edri-2025.12.3.dist-info/WHEEL
edri-2025.12.3.dist-info/top_level.txt
edri-2025.12.3.dist-info/RECORD
