Metadata-Version: 2.4
Name: edri
Version: 2025.12.3
Summary: Event Driven Routing Infrastructure
Author: Marek Olšan
Author-email: marek.olsan@gmail.com
Classifier: Development Status :: 5 - Production/Stable
Classifier: License :: OSI Approved :: MIT License
Classifier: Programming Language :: Python :: 3
Classifier: Programming Language :: Python :: 3.12
Classifier: Programming Language :: Python :: 3.13
Classifier: Programming Language :: Python :: 3.14
Classifier: Operating System :: POSIX
Classifier: Operating System :: POSIX :: Linux
Classifier: Intended Audience :: Developers
Classifier: Natural Language :: English
Classifier: Typing :: Typed
Requires-Dist: typeguard>=4.0
Requires-Dist: requests>=2.0
Requires-Dist: validators>=0.22.0
Requires-Dist: typing_extensions>=4.0
Requires-Dist: multipart>=1.0
Requires-Dist: jinja2>=3.1
Requires-Dist: watchdog>=6
Requires-Dist: websockets>=14
Requires-Dist: posix-ipc>=1.2.0
Requires-Dist: markdown>=3.0
Requires-Dist: pytz>=2024.1
Provides-Extra: uvicorn
Requires-Dist: uvicorn[standard]>=0.32.0; extra == "uvicorn"
Provides-Extra: hypercorn
Requires-Dist: hypercorn>=0.17.0; extra == "hypercorn"
Provides-Extra: dev
Requires-Dist: uvicorn>=0.32.0; extra == "dev"
Requires-Dist: hypercorn>=0.17.0; extra == "dev"
Requires-Dist: sphinx>=8.0.0; extra == "dev"
Requires-Dist: sphinx-autodoc-typehints>=3.0.0; extra == "dev"
Requires-Dist: sphinx_rtd_theme>=2.0.0; extra == "dev"
Requires-Dist: wheel; extra == "dev"
Requires-Dist: coverage; extra == "dev"
Requires-Dist: setuptools; extra == "dev"
Requires-Dist: twine; extra == "dev"
Dynamic: author
Dynamic: author-email
Dynamic: classifier
Dynamic: description
Dynamic: description-content-type
Dynamic: provides-extra
Dynamic: requires-dist
Dynamic: summary
